{
    "name": "Split-0_GNN_homogen_minibatch_SAGEConv_True-30_2022-05-22_16-41-07",
    "loss_name": "binary",
    "model_id": 30,
    "training": {
        "0": {
            "0": {
                "loss": 0.8931419849395752,
                "roc_auc": 0.8029779433334533
            },
            "1": {
                "loss": 0.7167280316352844,
                "roc_auc": 0.4977220222370158
            },
            "2": {
                "loss": 0.6650781631469727,
                "roc_auc": 0.786154712949641
            },
            "3": {
                "loss": 0.6025723218917847,
                "roc_auc": 0.7767529997331821
            },
            "4": {
                "loss": 0.5024392008781433,
                "roc_auc": 0.6744491831276225
            },
            "5": {
                "loss": 0.37082064151763916,
                "roc_auc": 0.2872421159038017
            },
            "6": {
                "loss": 0.23319053649902344,
                "roc_auc": 0.21893990970186109
            },
            "7": {
                "loss": 0.13909265398979187,
                "roc_auc": 0.21053844431326835
            },
            "8": {
                "loss": 0.11505502462387085,
                "roc_auc": 0.2080331867379528
            },
            "9": {
                "loss": 0.13458584249019623,
                "roc_auc": 0.2096683372869262
            },
            "10": {
                "loss": 0.16609346866607666,
                "roc_auc": 0.2091294905410842
            },
            "11": {
                "loss": 0.19035734236240387,
                "roc_auc": 0.21279262085153292
            },
            "12": {
                "loss": 0.20193400979042053,
                "roc_auc": 0.21669392347266228
            },
            "13": {
                "loss": 0.19894462823867798,
                "roc_auc": 0.23421488303688512
            },
            "14": {
                "loss": 0.18475909531116486,
                "roc_auc": 0.294703118558136
            },
            "15": {
                "loss": 0.1599350869655609,
                "roc_auc": 0.46960604060998995
            },
            "16": {
                "loss": 0.12781286239624023,
                "roc_auc": 0.7092144046667352
            }
        },
        "1": {
            "0": {
                "loss": 0.09546761959791183,
                "roc_auc": 0.7721831097129789
            },
            "1": {
                "loss": 0.10158519446849823,
                "roc_auc": 0.776787578722647
            },
            "2": {
                "loss": 0.13952749967575073,
                "roc_auc": 0.778857100005572
            },
            "3": {
                "loss": 0.0889415591955185,
                "roc_auc": 0.7764847928684424
            },
            "4": {
                "loss": 0.08492700755596161,
                "roc_auc": 0.7743853072260164
            },
            "5": {
                "loss": 0.09293197095394135,
                "roc_auc": 0.7647461820545145
            },
            "6": {
                "loss": 0.09860427677631378,
                "roc_auc": 0.7420698936994142
            },
            "7": {
                "loss": 0.10191313922405243,
                "roc_auc": 0.707391005031682
            },
            "8": {
                "loss": 0.10023166984319687,
                "roc_auc": 0.6819388557019137
            },
            "9": {
                "loss": 0.0963294580578804,
                "roc_auc": 0.6789571341977326
            },
            "10": {
                "loss": 0.09209910035133362,
                "roc_auc": 0.6898791249499173
            },
            "11": {
                "loss": 0.08685998618602753,
                "roc_auc": 0.7142241067197733
            },
            "12": {
                "loss": 0.08287720382213593,
                "roc_auc": 0.7376189744800932
            },
            "13": {
                "loss": 0.08124756813049316,
                "roc_auc": 0.7563926783481656
            },
            "14": {
                "loss": 0.08281174302101135,
                "roc_auc": 0.7661525758732143
            },
            "15": {
                "loss": 0.08574560284614563,
                "roc_auc": 0.7705851880893864
            },
            "16": {
                "loss": 0.08743943274021149,
                "roc_auc": 0.7725148608469355
            }
        },
        "2": {
            "0": {
                "loss": 0.08660153299570084,
                "roc_auc": 0.7735073841253449
            },
            "1": {
                "loss": 0.08332721889019012,
                "roc_auc": 0.7718055982464178
            },
            "2": {
                "loss": 0.07970353215932846,
                "roc_auc": 0.7695111817015686
            },
            "3": {
                "loss": 0.0775681585073471,
                "roc_auc": 0.7639726618793692
            },
            "4": {
                "loss": 0.0771171897649765,
                "roc_auc": 0.7588406267981951
            },
            "5": {
                "loss": 0.07777261734008789,
                "roc_auc": 0.7536910741221762
            },
            "6": {
                "loss": 0.07800179719924927,
                "roc_auc": 0.7537971685798556
            },
            "7": {
                "loss": 0.07884790748357773,
                "roc_auc": 0.754692011871174
            },
            "8": {
                "loss": 0.07765812426805496,
                "roc_auc": 0.758850741675463
            },
            "9": {
                "loss": 0.07603450119495392,
                "roc_auc": 0.7657877097206122
            },
            "10": {
                "loss": 0.07490979135036469,
                "roc_auc": 0.7706164077238636
            },
            "11": {
                "loss": 0.07344210892915726,
                "roc_auc": 0.7748249350920468
            },
            "12": {
                "loss": 0.07297711074352264,
                "roc_auc": 0.7772660116430694
            },
            "13": {
                "loss": 0.0735158696770668,
                "roc_auc": 0.7792720464006587
            },
            "14": {
                "loss": 0.07445873320102692,
                "roc_auc": 0.7806658007566031
            },
            "15": {
                "loss": 0.07423085719347,
                "roc_auc": 0.7806792110580869
            },
            "16": {
                "loss": 0.07273589819669724,
                "roc_auc": 0.7802569539375549
            }
        },
        "3": {
            "0": {
                "loss": 0.07179778069257736,
                "roc_auc": 0.7803284211892583
            },
            "1": {
                "loss": 0.07152773439884186,
                "roc_auc": 0.7792363934573254
            },
            "2": {
                "loss": 0.07176129519939423,
                "roc_auc": 0.7794780474303107
            },
            "3": {
                "loss": 0.07216674089431763,
                "roc_auc": 0.7789069656102164
            },
            "4": {
                "loss": 0.07202981412410736,
                "roc_auc": 0.7796700122013355
            },
            "5": {
                "loss": 0.07157155126333237,
                "roc_auc": 0.7803157504357917
            },
            "6": {
                "loss": 0.0704227089881897,
                "roc_auc": 0.7827267273946483
            },
            "7": {
                "loss": 0.07070157676935196,
                "roc_auc": 0.7831785902523932
            },
            "8": {
                "loss": 0.07042860984802246,
                "roc_auc": 0.7843312989842963
            },
            "9": {
                "loss": 0.07049957662820816,
                "roc_auc": 0.7859595731500559
            },
            "10": {
                "loss": 0.07069751620292664,
                "roc_auc": 0.786099187320937
            },
            "11": {
                "loss": 0.07010304927825928,
                "roc_auc": 0.7858773196570499
            },
            "12": {
                "loss": 0.0696450024843216,
                "roc_auc": 0.7851550810346342
            },
            "13": {
                "loss": 0.06945712119340897,
                "roc_auc": 0.7845732129944539
            },
            "14": {
                "loss": 0.06972724199295044,
                "roc_auc": 0.7847574998464156
            },
            "15": {
                "loss": 0.06971883773803711,
                "roc_auc": 0.7845351236145478
            },
            "16": {
                "loss": 0.06914092600345612,
                "roc_auc": 0.7849849076575246
            }
        },
        "4": {
            "0": {
                "loss": 0.06889625638723373,
                "roc_auc": 0.7869574407049543
            },
            "1": {
                "loss": 0.06855019181966782,
                "roc_auc": 0.7879230949083632
            },
            "2": {
                "loss": 0.06837841868400574,
                "roc_auc": 0.7899504381798982
            },
            "3": {
                "loss": 0.06842289865016937,
                "roc_auc": 0.7905147923293436
            },
            "4": {
                "loss": 0.06826895475387573,
                "roc_auc": 0.7913046230248978
            },
            "5": {
                "loss": 0.06815032660961151,
                "roc_auc": 0.7908588778882235
            },
            "6": {
                "loss": 0.06756126135587692,
                "roc_auc": 0.7918375752188707
            },
            "7": {
                "loss": 0.0680384486913681,
                "roc_auc": 0.7904946290082401
            },
            "8": {
                "loss": 0.06750994175672531,
                "roc_auc": 0.7904336755858747
            },
            "9": {
                "loss": 0.06724470108747482,
                "roc_auc": 0.7916652604607607
            },
            "10": {
                "loss": 0.06756102293729782,
                "roc_auc": 0.7927574984967867
            },
            "11": {
                "loss": 0.06734497100114822,
                "roc_auc": 0.7941816432788944
            },
            "12": {
                "loss": 0.06714871525764465,
                "roc_auc": 0.7961672478512779
            },
            "13": {
                "loss": 0.06699593365192413,
                "roc_auc": 0.7973992801906191
            },
            "14": {
                "loss": 0.0670713409781456,
                "roc_auc": 0.7989855862966865
            },
            "15": {
                "loss": 0.0669902041554451,
                "roc_auc": 0.799110146001253
            },
            "16": {
                "loss": 0.0666080191731453,
                "roc_auc": 0.7988449801182527
            }
        },
        "5": {
            "0": {
                "loss": 0.06662672013044357,
                "roc_auc": 0.8002691900429414
            },
            "1": {
                "loss": 0.06640516221523285,
                "roc_auc": 0.8006113991797423
            },
            "2": {
                "loss": 0.06615230441093445,
                "roc_auc": 0.8026598493283466
            },
            "3": {
                "loss": 0.06608995050191879,
                "roc_auc": 0.8043610742739341
            },
            "4": {
                "loss": 0.06601940095424652,
                "roc_auc": 0.8070801863639325
            },
            "5": {
                "loss": 0.06609591096639633,
                "roc_auc": 0.8088247949008747
            },
            "6": {
                "loss": 0.06563907116651535,
                "roc_auc": 0.81186420901262
            },
            "7": {
                "loss": 0.066041000187397,
                "roc_auc": 0.8117176432450482
            },
            "8": {
                "loss": 0.06548786163330078,
                "roc_auc": 0.8120767025334473
            },
            "9": {
                "loss": 0.06529638171195984,
                "roc_auc": 0.8133863124360664
            },
            "10": {
                "loss": 0.0656898096203804,
                "roc_auc": 0.8148350578745017
            },
            "11": {
                "loss": 0.06555327773094177,
                "roc_auc": 0.8162180462444462
            },
            "12": {
                "loss": 0.06533585488796234,
                "roc_auc": 0.8189612298290823
            },
            "13": {
                "loss": 0.06518067419528961,
                "roc_auc": 0.8204515147993644
            },
            "14": {
                "loss": 0.0652846097946167,
                "roc_auc": 0.8225992908355737
            },
            "15": {
                "loss": 0.06525985151529312,
                "roc_auc": 0.8232833787249807
            },
            "16": {
                "loss": 0.06494586169719696,
                "roc_auc": 0.8232739579397418
            }
        },
        "6": {
            "0": {
                "loss": 0.06497939676046371,
                "roc_auc": 0.8252649291989143
            },
            "1": {
                "loss": 0.06474717706441879,
                "roc_auc": 0.8262783161042079
            },
            "2": {
                "loss": 0.06453172862529755,
                "roc_auc": 0.828161804116147
            },
            "3": {
                "loss": 0.06452251225709915,
                "roc_auc": 0.8292112874441976
            },
            "4": {
                "loss": 0.06448599696159363,
                "roc_auc": 0.830815958124608
            },
            "5": {
                "loss": 0.06455104798078537,
                "roc_auc": 0.8313021072582594
            },
            "6": {
                "loss": 0.0641004890203476,
                "roc_auc": 0.8334398022827897
            },
            "7": {
                "loss": 0.06454383581876755,
                "roc_auc": 0.833261256959947
            },
            "8": {
                "loss": 0.06401972472667694,
                "roc_auc": 0.8338886619508031
            },
            "9": {
                "loss": 0.06384950131177902,
                "roc_auc": 0.8352008735863031
            },
            "10": {
                "loss": 0.06421396136283875,
                "roc_auc": 0.8366730328418369
            },
            "11": {
                "loss": 0.0641198679804802,
                "roc_auc": 0.8370449359013974
            },
            "12": {
                "loss": 0.06391863524913788,
                "roc_auc": 0.838527244161391
            },
            "13": {
                "loss": 0.0637722909450531,
                "roc_auc": 0.8387493122802098
            },
            "14": {
                "loss": 0.06387785822153091,
                "roc_auc": 0.840525626304139
            },
            "15": {
                "loss": 0.06386703252792358,
                "roc_auc": 0.8412755953684001
            },
            "16": {
                "loss": 0.06359867006540298,
                "roc_auc": 0.8411630507188663
            }
        },
        "7": {
            "0": {
                "loss": 0.06362130492925644,
                "roc_auc": 0.8432364133178999
            },
            "1": {
                "loss": 0.06338081508874893,
                "roc_auc": 0.8443177211344945
            },
            "2": {
                "loss": 0.0631990134716034,
                "roc_auc": 0.8454103983729904
            },
            "3": {
                "loss": 0.06319408863782883,
                "roc_auc": 0.8460899377060441
            },
            "4": {
                "loss": 0.06316845118999481,
                "roc_auc": 0.8473635246021433
            },
            "5": {
                "loss": 0.06323861330747604,
                "roc_auc": 0.8480843411146708
            },
            "6": {
                "loss": 0.06280181556940079,
                "roc_auc": 0.8503329236841634
            },
            "7": {
                "loss": 0.06322424113750458,
                "roc_auc": 0.8502681155605292
            },
            "8": {
                "loss": 0.06272240728139877,
                "roc_auc": 0.8508358250473343
            },
            "9": {
                "loss": 0.06257236003875732,
                "roc_auc": 0.8518130350786758
            },
            "10": {
                "loss": 0.06291835010051727,
                "roc_auc": 0.8533167395883722
            },
            "11": {
                "loss": 0.06283741444349289,
                "roc_auc": 0.8536604433065931
            },
            "12": {
                "loss": 0.0626334622502327,
                "roc_auc": 0.8551498208888965
            },
            "13": {
                "loss": 0.06250359117984772,
                "roc_auc": 0.8553485898188378
            },
            "14": {
                "loss": 0.06260498613119125,
                "roc_auc": 0.8572124909944585
            },
            "15": {
                "loss": 0.06259264796972275,
                "roc_auc": 0.8578873088643809
            },
            "16": {
                "loss": 0.0623616985976696,
                "roc_auc": 0.8573613696268606
            }
        },
        "8": {
            "0": {
                "loss": 0.06237351894378662,
                "roc_auc": 0.859392282718611
            },
            "1": {
                "loss": 0.06211494281888008,
                "roc_auc": 0.8608343950876413
            },
            "2": {
                "loss": 0.06195729970932007,
                "roc_auc": 0.8615997818716079
            },
            "3": {
                "loss": 0.06195404380559921,
                "roc_auc": 0.862222467714038
            },
            "4": {
                "loss": 0.06195135787129402,
                "roc_auc": 0.8629131418802959
            },
            "5": {
                "loss": 0.062016088515520096,
                "roc_auc": 0.8637098395561376
            },
            "6": {
                "loss": 0.06158618628978729,
                "roc_auc": 0.8657520585980157
            },
            "7": {
                "loss": 0.06198957562446594,
                "roc_auc": 0.8657649747886168
            },
            "8": {
                "loss": 0.06150691211223602,
                "roc_auc": 0.8663118203627624
            },
            "9": {
                "loss": 0.06137223169207573,
                "roc_auc": 0.8668766814510852
            },
            "10": {
                "loss": 0.06171344965696335,
                "roc_auc": 0.8680867933357849
            },
            "11": {
                "loss": 0.061644624918699265,
                "roc_auc": 0.8683756513323676
            },
            "12": {
                "loss": 0.06142812967300415,
                "roc_auc": 0.8696839076614079
            },
            "13": {
                "loss": 0.06132613122463226,
                "roc_auc": 0.8694568707533914
            },
            "14": {
                "loss": 0.0614187978208065,
                "roc_auc": 0.8713253193998063
            },
            "15": {
                "loss": 0.06141115725040436,
                "roc_auc": 0.8718858107983177
            },
            "16": {
                "loss": 0.061214108020067215,
                "roc_auc": 0.8708577478777679
            }
        },
        "9": {
            "0": {
                "loss": 0.06122138723731041,
                "roc_auc": 0.8726857896508581
            },
            "1": {
                "loss": 0.06094648316502571,
                "roc_auc": 0.8744112361008607
            },
            "2": {
                "loss": 0.060816578567028046,
                "roc_auc": 0.874427776227752
            },
            "3": {
                "loss": 0.06081290543079376,
                "roc_auc": 0.8749044490969309
            },
            "4": {
                "loss": 0.06085235998034477,
                "roc_auc": 0.8751403848780723
            },
            "5": {
                "loss": 0.06091470271348953,
                "roc_auc": 0.8756943318202329
            },
            "6": {
                "loss": 0.06048957630991936,
                "roc_auc": 0.8773729170443272
            },
            "7": {
                "loss": 0.06087956205010414,
                "roc_auc": 0.8774738170679456
            },
            "8": {
                "loss": 0.060418501496315,
                "roc_auc": 0.877858948987095
            },
            "9": {
                "loss": 0.06031089276075363,
                "roc_auc": 0.8779913052785558
            },
            "10": {
                "loss": 0.06065057963132858,
                "roc_auc": 0.8789080570229673
            },
            "11": {
                "loss": 0.06061851233243942,
                "roc_auc": 0.8788574046948628
            },
            "12": {
                "loss": 0.060404758900403976,
                "roc_auc": 0.8799276580824944
            },
            "13": {
                "loss": 0.060365837067365646,
                "roc_auc": 0.8795448883457344
            },
            "14": {
                "loss": 0.060498252511024475,
                "roc_auc": 0.8808713137388123
            },
            "15": {
                "loss": 0.060532115399837494,
                "roc_auc": 0.8815604464556719
            },
            "16": {
                "loss": 0.06051764637231827,
                "roc_auc": 0.8797803477722327
            }
        },
        "10": {
            "0": {
                "loss": 0.060603585094213486,
                "roc_auc": 0.8820653778118158
            },
            "1": {
                "loss": 0.06073537468910217,
                "roc_auc": 0.8825174579839219
            },
            "2": {
                "loss": 0.060688555240631104,
                "roc_auc": 0.8833106182302807
            },
            "3": {
                "loss": 0.06162823364138603,
                "roc_auc": 0.8821636227400629
            },
            "4": {
                "loss": 0.06070134416222572,
                "roc_auc": 0.883134825727805
            },
            "5": {
                "loss": 0.060594264417886734,
                "roc_auc": 0.8827007401163977
            },
            "6": {
                "loss": 0.05983567237854004,
                "roc_auc": 0.8846212709793121
            },
            "7": {
                "loss": 0.06011924892663956,
                "roc_auc": 0.8843493161178033
            },
            "8": {
                "loss": 0.05966311693191528,
                "roc_auc": 0.8846264536060368
            },
            "9": {
                "loss": 0.05960511788725853,
                "roc_auc": 0.8845851728651887
            },
            "10": {
                "loss": 0.060041725635528564,
                "roc_auc": 0.8848559902372654
            },
            "11": {
                "loss": 0.06021988019347191,
                "roc_auc": 0.8849604442789566
            },
            "12": {
                "loss": 0.06060468778014183,
                "roc_auc": 0.8853144205164729
            },
            "13": {
                "loss": 0.06084536388516426,
                "roc_auc": 0.8853454223462539
            },
            "14": {
                "loss": 0.0629788339138031,
                "roc_auc": 0.8851909225995017
            },
            "15": {
                "loss": 0.060493383556604385,
                "roc_auc": 0.8868594655853212
            },
            "16": {
                "loss": 0.059743091464042664,
                "roc_auc": 0.8850705457614371
            }
        },
        "11": {
            "0": {
                "loss": 0.05990908294916153,
                "roc_auc": 0.8861898168426476
            },
            "1": {
                "loss": 0.06024118885397911,
                "roc_auc": 0.8882348851362349
            },
            "2": {
                "loss": 0.061874765902757645,
                "roc_auc": 0.8861024117434013
            },
            "3": {
                "loss": 0.05991775915026665,
                "roc_auc": 0.8877376054149689
            },
            "4": {
                "loss": 0.05956346169114113,
                "roc_auc": 0.8867341629640224
            },
            "5": {
                "loss": 0.06011743098497391,
                "roc_auc": 0.8867400585211593
            },
            "6": {
                "loss": 0.06016629561781883,
                "roc_auc": 0.8885808136148678
            },
            "7": {
                "loss": 0.06157854571938515,
                "roc_auc": 0.887428626919702
            },
            "8": {
                "loss": 0.05953367054462433,
                "roc_auc": 0.888501214954161
            },
            "9": {
                "loss": 0.0593440905213356,
                "roc_auc": 0.888171336792001
            },
            "10": {
                "loss": 0.060727816075086594,
                "roc_auc": 0.887881080402308
            },
            "11": {
                "loss": 0.06033574417233467,
                "roc_auc": 0.8883540992556952
            },
            "12": {
                "loss": 0.05985228344798088,
                "roc_auc": 0.8887508378293266
            },
            "13": {
                "loss": 0.05939537659287453,
                "roc_auc": 0.8880053650106507
            },
            "14": {
                "loss": 0.05976102501153946,
                "roc_auc": 0.8895725460493282
            },
            "15": {
                "loss": 0.060377687215805054,
                "roc_auc": 0.8889927988010375
            },
            "16": {
                "loss": 0.059684619307518005,
                "roc_auc": 0.8883971257688686
            }
        },
        "12": {
            "0": {
                "loss": 0.059443358331918716,
                "roc_auc": 0.8892598656234438
            },
            "1": {
                "loss": 0.05927085131406784,
                "roc_auc": 0.8904972956636809
            },
            "2": {
                "loss": 0.05942744016647339,
                "roc_auc": 0.8900018924197391
            },
            "3": {
                "loss": 0.05952104553580284,
                "roc_auc": 0.8898504083030797
            },
            "4": {
                "loss": 0.05934740975499153,
                "roc_auc": 0.8895208619327837
            },
            "5": {
                "loss": 0.05938802286982536,
                "roc_auc": 0.8897945566658398
            },
            "6": {
                "loss": 0.05915326997637749,
                "roc_auc": 0.8906659801965852
            },
            "7": {
                "loss": 0.05954079329967499,
                "roc_auc": 0.8910057041508592
            },
            "8": {
                "loss": 0.05905728414654732,
                "roc_auc": 0.8907558489216295
            },
            "9": {
                "loss": 0.05893528461456299,
                "roc_auc": 0.8905901172376814
            },
            "10": {
                "loss": 0.05930104851722717,
                "roc_auc": 0.8910578101870602
            },
            "11": {
                "loss": 0.05935800075531006,
                "roc_auc": 0.8904948623131045
            },
            "12": {
                "loss": 0.059128288179636,
                "roc_auc": 0.8917387476501009
            },
            "13": {
                "loss": 0.05914483591914177,
                "roc_auc": 0.8904455431125614
            },
            "14": {
                "loss": 0.059213701635599136,
                "roc_auc": 0.8918976696598289
            },
            "15": {
                "loss": 0.05918901413679123,
                "roc_auc": 0.8920177251246628
            },
            "16": {
                "loss": 0.05910520628094673,
                "roc_auc": 0.8907143494680697
            }
        },
        "13": {
            "0": {
                "loss": 0.05915582925081253,
                "roc_auc": 0.8918468363650791
            },
            "1": {
                "loss": 0.058879658579826355,
                "roc_auc": 0.8930995062387408
            },
            "2": {
                "loss": 0.058890920132398605,
                "roc_auc": 0.8922975614824299
            },
            "3": {
                "loss": 0.05890515819191933,
                "roc_auc": 0.8925169917147071
            },
            "4": {
                "loss": 0.0590808130800724,
                "roc_auc": 0.8919315110085521
            },
            "5": {
                "loss": 0.059281352907419205,
                "roc_auc": 0.8919868596112945
            },
            "6": {
                "loss": 0.05900642275810242,
                "roc_auc": 0.8933747131197349
            },
            "7": {
                "loss": 0.05995839089155197,
                "roc_auc": 0.8928991543070439
            },
            "8": {
                "loss": 0.059811823070049286,
                "roc_auc": 0.8935605438741331
            },
            "9": {
                "loss": 0.06185097619891167,
                "roc_auc": 0.8920886336838308
            },
            "10": {
                "loss": 0.059650685638189316,
                "roc_auc": 0.8934684846318195
            },
            "11": {
                "loss": 0.05904644355177879,
                "roc_auc": 0.8927807315506889
            },
            "12": {
                "loss": 0.05894380062818527,
                "roc_auc": 0.8937080393091357
            },
            "13": {
                "loss": 0.059607163071632385,
                "roc_auc": 0.89294308688874
            },
            "14": {
                "loss": 0.0616428442299366,
                "roc_auc": 0.8932500781067657
            },
            "15": {
                "loss": 0.05972206965088844,
                "roc_auc": 0.8943749885430905
            },
            "16": {
                "loss": 0.05905154347419739,
                "roc_auc": 0.8926989562810022
            }
        },
        "14": {
            "0": {
                "loss": 0.058887381106615067,
                "roc_auc": 0.8937897307011764
            },
            "1": {
                "loss": 0.05891500040888786,
                "roc_auc": 0.8952896643421028
            },
            "2": {
                "loss": 0.059712864458560944,
                "roc_auc": 0.8936692390445993
            },
            "3": {
                "loss": 0.05916661024093628,
                "roc_auc": 0.8947086323538552
            },
            "4": {
                "loss": 0.05910031870007515,
                "roc_auc": 0.8934838215918642
            },
            "5": {
                "loss": 0.058883193880319595,
                "roc_auc": 0.8939677540381915
            },
            "6": {
                "loss": 0.058556728065013885,
                "roc_auc": 0.8950696722126221
            },
            "7": {
                "loss": 0.05934005603194237,
                "roc_auc": 0.894760170374949
            },
            "8": {
                "loss": 0.05899462476372719,
                "roc_auc": 0.8952117720267286
            },
            "9": {
                "loss": 0.05912996456027031,
                "roc_auc": 0.8942237409186095
            },
            "10": {
                "loss": 0.05890132859349251,
                "roc_auc": 0.8950704102108827
            },
            "11": {
                "loss": 0.058878764510154724,
                "roc_auc": 0.8946160472350112
            },
            "12": {
                "loss": 0.05905766412615776,
                "roc_auc": 0.8952859496209511
            },
            "13": {
                "loss": 0.05915825068950653,
                "roc_auc": 0.8946356349809831
            },
            "14": {
                "loss": 0.05944313481450081,
                "roc_auc": 0.895323953503992
            },
            "15": {
                "loss": 0.05889783427119255,
                "roc_auc": 0.8960008825089189
            },
            "16": {
                "loss": 0.058631982654333115,
                "roc_auc": 0.8946585558819774
            }
        },
        "15": {
            "0": {
                "loss": 0.05881209298968315,
                "roc_auc": 0.8954737732138858
            },
            "1": {
                "loss": 0.05874279513955116,
                "roc_auc": 0.8970556050884453
            },
            "2": {
                "loss": 0.05907759442925453,
                "roc_auc": 0.8955513398625742
            },
            "3": {
                "loss": 0.058658625930547714,
                "roc_auc": 0.8964071324591293
            },
            "4": {
                "loss": 0.0586128756403923,
                "roc_auc": 0.8954023145257158
            },
            "5": {
                "loss": 0.058649055659770966,
                "roc_auc": 0.8956898611935172
            },
            "6": {
                "loss": 0.05837608873844147,
                "roc_auc": 0.8968766809396646
            },
            "7": {
                "loss": 0.0590735599398613,
                "roc_auc": 0.8966159238922784
            },
            "8": {
                "loss": 0.05873939022421837,
                "roc_auc": 0.8969956266992055
            },
            "9": {
                "loss": 0.059012606739997864,
                "roc_auc": 0.8959988671820736
            },
            "10": {
                "loss": 0.05882452428340912,
                "roc_auc": 0.8968630759239516
            },
            "11": {
                "loss": 0.05863098055124283,
                "roc_auc": 0.8962853260721663
            },
            "12": {
                "loss": 0.05839305743575096,
                "roc_auc": 0.8972388703158503
            },
            "13": {
                "loss": 0.05861031264066696,
                "roc_auc": 0.8963255763970784
            },
            "14": {
                "loss": 0.05914444476366043,
                "roc_auc": 0.8970932732455877
            },
            "15": {
                "loss": 0.059135209769010544,
                "roc_auc": 0.897825626899273
            },
            "16": {
                "loss": 0.05956067144870758,
                "roc_auc": 0.8960822770471938
            }
        },
        "16": {
            "0": {
                "loss": 0.05893639102578163,
                "roc_auc": 0.8974807451451694
            },
            "1": {
                "loss": 0.05844704061746597,
                "roc_auc": 0.8984038582305233
            },
            "2": {
                "loss": 0.05824270471930504,
                "roc_auc": 0.8975843810570244
            },
            "3": {
                "loss": 0.05816346034407616,
                "roc_auc": 0.8979137829548401
            },
            "4": {
                "loss": 0.058368563652038574,
                "roc_auc": 0.8970862166602671
            },
            "5": {
                "loss": 0.05857475847005844,
                "roc_auc": 0.8974105077387255
            },
            "6": {
                "loss": 0.05838916078209877,
                "roc_auc": 0.8982476092576142
            },
            "7": {
                "loss": 0.058790188282728195,
                "roc_auc": 0.8986103602798359
            },
            "8": {
                "loss": 0.05865652859210968,
                "roc_auc": 0.898187544883668
            },
            "9": {
                "loss": 0.05850807949900627,
                "roc_auc": 0.8980646546505524
            },
            "10": {
                "loss": 0.059206772595644,
                "roc_auc": 0.898041581590121
            },
            "11": {
                "loss": 0.05907880514860153,
                "roc_auc": 0.8980942526535434
            },
            "12": {
                "loss": 0.0594189390540123,
                "roc_auc": 0.898479135418927
            },
            "13": {
                "loss": 0.05889800935983658,
                "roc_auc": 0.8979534619216054
            },
            "14": {
                "loss": 0.05917012691497803,
                "roc_auc": 0.898568105165584
            },
            "15": {
                "loss": 0.058692749589681625,
                "roc_auc": 0.8993172045380939
            },
            "16": {
                "loss": 0.05854175239801407,
                "roc_auc": 0.8978335269950549
            }
        },
        "17": {
            "0": {
                "loss": 0.05838843062520027,
                "roc_auc": 0.8989289439024976
            },
            "1": {
                "loss": 0.05802364647388458,
                "roc_auc": 0.9000071661051333
            },
            "2": {
                "loss": 0.057997558265924454,
                "roc_auc": 0.8990389589250041
            },
            "3": {
                "loss": 0.05796586722135544,
                "roc_auc": 0.8994086530597449
            },
            "4": {
                "loss": 0.05814196169376373,
                "roc_auc": 0.8986302661871561
            },
            "5": {
                "loss": 0.05827938765287399,
                "roc_auc": 0.8988619414743738
            },
            "6": {
                "loss": 0.05793362855911255,
                "roc_auc": 0.899843560029679
            },
            "7": {
                "loss": 0.05834445357322693,
                "roc_auc": 0.9000851135915808
            },
            "8": {
                "loss": 0.05804067105054855,
                "roc_auc": 0.8998303789467544
            },
            "9": {
                "loss": 0.05810239911079407,
                "roc_auc": 0.8995141264893702
            },
            "10": {
                "loss": 0.05886118859052658,
                "roc_auc": 0.899588168130614
            },
            "11": {
                "loss": 0.05916823446750641,
                "roc_auc": 0.8996355188042643
            },
            "12": {
                "loss": 0.060866016894578934,
                "roc_auc": 0.8997663536008139
            },
            "13": {
                "loss": 0.059167277067899704,
                "roc_auc": 0.8995145518415675
            },
            "14": {
                "loss": 0.059385593980550766,
                "roc_auc": 0.8999930356471614
            },
            "15": {
                "loss": 0.05852368846535683,
                "roc_auc": 0.9008368599223522
            },
            "16": {
                "loss": 0.058240555226802826,
                "roc_auc": 0.899409740606773
            }
        },
        "18": {
            "0": {
                "loss": 0.058113694190979004,
                "roc_auc": 0.9004016720511429
            },
            "1": {
                "loss": 0.057778749614953995,
                "roc_auc": 0.9015545387789782
            },
            "2": {
                "loss": 0.05782312899827957,
                "roc_auc": 0.9004604364446968
            },
            "3": {
                "loss": 0.057870566844940186,
                "roc_auc": 0.9009313844403705
            },
            "4": {
                "loss": 0.05818646028637886,
                "roc_auc": 0.9000179284591817
            },
            "5": {
                "loss": 0.05838831141591072,
                "roc_auc": 0.9003751221193094
            },
            "6": {
                "loss": 0.05834127962589264,
                "roc_auc": 0.9011597341945382
            },
            "7": {
                "loss": 0.05856407806277275,
                "roc_auc": 0.9016165762387859
            },
            "8": {
                "loss": 0.05844207853078842,
                "roc_auc": 0.9011325701047082
            },
            "9": {
                "loss": 0.05813999101519585,
                "roc_auc": 0.9009353899744299
            },
            "10": {
                "loss": 0.058668892830610275,
                "roc_auc": 0.9009850278034255
            },
            "11": {
                "loss": 0.05853563919663429,
                "roc_auc": 0.9009868116670788
            },
            "12": {
                "loss": 0.058631498366594315,
                "roc_auc": 0.9014426855967169
            },
            "13": {
                "loss": 0.05840376392006874,
                "roc_auc": 0.9008507430022777
            },
            "14": {
                "loss": 0.058783236891031265,
                "roc_auc": 0.9014135505656056
            },
            "15": {
                "loss": 0.05841713398694992,
                "roc_auc": 0.9022406986849193
            },
            "16": {
                "loss": 0.058468036353588104,
                "roc_auc": 0.9007454459403406
            }
        },
        "19": {
            "0": {
                "loss": 0.058218758553266525,
                "roc_auc": 0.9018629418581237
            },
            "1": {
                "loss": 0.05789614096283913,
                "roc_auc": 0.9027869565840532
            },
            "2": {
                "loss": 0.05777667835354805,
                "roc_auc": 0.9019741874903883
            },
            "3": {
                "loss": 0.05771892890334129,
                "roc_auc": 0.9021201285213438
            },
            "4": {
                "loss": 0.05782870203256607,
                "roc_auc": 0.9015899450949107
            },
            "5": {
                "loss": 0.05793243646621704,
                "roc_auc": 0.9015651595047481
            },
            "6": {
                "loss": 0.057526882737874985,
                "roc_auc": 0.9028166448629653
            },
            "7": {
                "loss": 0.05796905606985092,
                "roc_auc": 0.9027712777803242
            },
            "8": {
                "loss": 0.05769316107034683,
                "roc_auc": 0.9028954089732939
            },
            "9": {
                "loss": 0.05810628458857536,
                "roc_auc": 0.9019132646301321
            },
            "10": {
                "loss": 0.058511726558208466,
                "roc_auc": 0.9027047962395246
            },
            "11": {
                "loss": 0.05953487381339073,
                "roc_auc": 0.9018348275303003
            },
            "12": {
                "loss": 0.05876774340867996,
                "roc_auc": 0.9032656618630414
            },
            "13": {
                "loss": 0.059975653886795044,
                "roc_auc": 0.9015910146798107
            },
            "14": {
                "loss": 0.058545585721731186,
                "roc_auc": 0.9031548902594702
            },
            "15": {
                "loss": 0.05823197588324547,
                "roc_auc": 0.903236982486336
            },
            "16": {
                "loss": 0.057813167572021484,
                "roc_auc": 0.9023906956172932
            }
        },
        "20": {
            "0": {
                "loss": 0.05776960775256157,
                "roc_auc": 0.9030040803707052
            },
            "1": {
                "loss": 0.057437725365161896,
                "roc_auc": 0.9042984941030103
            },
            "2": {
                "loss": 0.05744902417063713,
                "roc_auc": 0.9031894380977944
            },
            "3": {
                "loss": 0.057427652180194855,
                "roc_auc": 0.903485283154769
            },
            "4": {
                "loss": 0.05759831890463829,
                "roc_auc": 0.902876412347341
            },
            "5": {
                "loss": 0.057751648128032684,
                "roc_auc": 0.9028535793845808
            },
            "6": {
                "loss": 0.05742054805159569,
                "roc_auc": 0.9041336558034849
            },
            "7": {
                "loss": 0.058076415210962296,
                "roc_auc": 0.9040062806705127
            },
            "8": {
                "loss": 0.05803325027227402,
                "roc_auc": 0.9042529972540155
            },
            "9": {
                "loss": 0.059650082141160965,
                "roc_auc": 0.9029128060291057
            },
            "10": {
                "loss": 0.05880437791347504,
                "roc_auc": 0.9039829294332727
            },
            "11": {
                "loss": 0.05935471132397652,
                "roc_auc": 0.9031010801302564
            },
            "12": {
                "loss": 0.0580889917910099,
                "roc_auc": 0.9044588753515621
            },
            "13": {
                "loss": 0.05802350118756294,
                "roc_auc": 0.9031210829462535
            },
            "14": {
                "loss": 0.0578087642788887,
                "roc_auc": 0.9043007531457324
            },
            "15": {
                "loss": 0.0576607771217823,
                "roc_auc": 0.9045986998238578
            },
            "16": {
                "loss": 0.05752578750252724,
                "roc_auc": 0.9036381822879253
            }
        },
        "21": {
            "0": {
                "loss": 0.057569295167922974,
                "roc_auc": 0.9042778673874656
            },
            "1": {
                "loss": 0.05728136748075485,
                "roc_auc": 0.9055649530358315
            },
            "2": {
                "loss": 0.057320695370435715,
                "roc_auc": 0.904417744964608
            },
            "3": {
                "loss": 0.05730874463915825,
                "roc_auc": 0.9047874651789665
            },
            "4": {
                "loss": 0.057502999901771545,
                "roc_auc": 0.9040585614869234
            },
            "5": {
                "loss": 0.057670190930366516,
                "roc_auc": 0.9042199340282513
            },
            "6": {
                "loss": 0.05745166540145874,
                "roc_auc": 0.9052052610252451
            },
            "7": {
                "loss": 0.05797474831342697,
                "roc_auc": 0.9055567299263526
            },
            "8": {
                "loss": 0.0584329217672348,
                "roc_auc": 0.905050740454791
            },
            "9": {
                "loss": 0.05850088968873024,
                "roc_auc": 0.9048339270983256
            },
            "10": {
                "loss": 0.06154899671673775,
                "roc_auc": 0.9044461313697044
            },
            "11": {
                "loss": 0.05860394239425659,
                "roc_auc": 0.9048944472317383
            },
            "12": {
                "loss": 0.057902637869119644,
                "roc_auc": 0.905331943578376
            },
            "13": {
                "loss": 0.05747956782579422,
                "roc_auc": 0.904628759708658
            },
            "14": {
                "loss": 0.057463373988866806,
                "roc_auc": 0.9053703392886302
            },
            "15": {
                "loss": 0.0573696568608284,
                "roc_auc": 0.9059167760796338
            },
            "16": {
                "loss": 0.05732633173465729,
                "roc_auc": 0.9048640549636193
            }
        },
        "22": {
            "0": {
                "loss": 0.05747968703508377,
                "roc_auc": 0.9054595090656126
            },
            "1": {
                "loss": 0.057346735149621964,
                "roc_auc": 0.906839824176384
            },
            "2": {
                "loss": 0.05782844498753548,
                "roc_auc": 0.9054509920197759
            },
            "3": {
                "loss": 0.05788121744990349,
                "roc_auc": 0.9060692658133346
            },
            "4": {
                "loss": 0.059047162532806396,
                "roc_auc": 0.9049523444335555
            },
            "5": {
                "loss": 0.058293018490076065,
                "roc_auc": 0.9054515113879837
            },
            "6": {
                "loss": 0.058110449463129044,
                "roc_auc": 0.9062157851755804
            },
            "7": {
                "loss": 0.05773488059639931,
                "roc_auc": 0.9067025209902106
            },
            "8": {
                "loss": 0.057119179517030716,
                "roc_auc": 0.9063942419586819
            },
            "9": {
                "loss": 0.05701259523630142,
                "roc_auc": 0.9057647994121052
            },
            "10": {
                "loss": 0.057316701859235764,
                "roc_auc": 0.9061749722289444
            },
            "11": {
                "loss": 0.057360295206308365,
                "roc_auc": 0.9058229101977239
            },
            "12": {
                "loss": 0.05716107040643692,
                "roc_auc": 0.9067045840046744
            },
            "13": {
                "loss": 0.05728457123041153,
                "roc_auc": 0.9056300288750062
            },
            "14": {
                "loss": 0.05746496096253395,
                "roc_auc": 0.90663473871464
            },
            "15": {
                "loss": 0.05765107274055481,
                "roc_auc": 0.9069343019485142
            },
            "16": {
                "loss": 0.057792868465185165,
                "roc_auc": 0.9061445038312024
            }
        },
        "23": {
            "0": {
                "loss": 0.05908060818910599,
                "roc_auc": 0.9063511579152498
            },
            "1": {
                "loss": 0.058366868644952774,
                "roc_auc": 0.9081218191163838
            },
            "2": {
                "loss": 0.06033343821763992,
                "roc_auc": 0.9062823587042838
            },
            "3": {
                "loss": 0.05766592547297478,
                "roc_auc": 0.9071903234970659
            },
            "4": {
                "loss": 0.05718199908733368,
                "roc_auc": 0.9064146969713203
            },
            "5": {
                "loss": 0.05724351480603218,
                "roc_auc": 0.9063991184165163
            },
            "6": {
                "loss": 0.05722736567258835,
                "roc_auc": 0.9077215980288932
            },
            "7": {
                "loss": 0.058914635330438614,
                "roc_auc": 0.9073590617805413
            },
            "8": {
                "loss": 0.05819712579250336,
                "roc_auc": 0.9078154461973764
            },
            "9": {
                "loss": 0.05952591076493263,
                "roc_auc": 0.9062699497321857
            },
            "10": {
                "loss": 0.05748863145709038,
                "roc_auc": 0.9073444771904527
            },
            "11": {
                "loss": 0.05741453543305397,
                "roc_auc": 0.9070033124077569
            },
            "12": {
                "loss": 0.05875374376773834,
                "roc_auc": 0.907266640934915
            },
            "13": {
                "loss": 0.058272045105695724,
                "roc_auc": 0.9069238747068936
            },
            "14": {
                "loss": 0.05875329300761223,
                "roc_auc": 0.907125250947522
            },
            "15": {
                "loss": 0.0572749488055706,
                "roc_auc": 0.9081462150402393
            },
            "16": {
                "loss": 0.05723318085074425,
                "roc_auc": 0.9070878329337475
            }
        },
        "24": {
            "0": {
                "loss": 0.05837677791714668,
                "roc_auc": 0.9072778117488959
            },
            "1": {
                "loss": 0.0575682558119297,
                "roc_auc": 0.9089778374183586
            },
            "2": {
                "loss": 0.05732882022857666,
                "roc_auc": 0.9075278778198255
            },
            "3": {
                "loss": 0.05687914043664932,
                "roc_auc": 0.9079036224535897
            },
            "4": {
                "loss": 0.05724867060780525,
                "roc_auc": 0.9074747849756771
            },
            "5": {
                "loss": 0.05801618844270706,
                "roc_auc": 0.907052824525272
            },
            "6": {
                "loss": 0.0571451336145401,
                "roc_auc": 0.9086425204782577
            },
            "7": {
                "loss": 0.05725041776895523,
                "roc_auc": 0.9085295416812003
            },
            "8": {
                "loss": 0.05671192705631256,
                "roc_auc": 0.9085284762530673
            },
            "9": {
                "loss": 0.05684652179479599,
                "roc_auc": 0.9077833534420312
            },
            "10": {
                "loss": 0.057443469762802124,
                "roc_auc": 0.9080329796557619
            },
            "11": {
                "loss": 0.057466164231300354,
                "roc_auc": 0.9079981199720325
            },
            "12": {
                "loss": 0.057279691100120544,
                "roc_auc": 0.9084849922570544
            },
            "13": {
                "loss": 0.05704456940293312,
                "roc_auc": 0.9078060020075543
            },
            "14": {
                "loss": 0.057036664336919785,
                "roc_auc": 0.908496129903605
            },
            "15": {
                "loss": 0.056957971304655075,
                "roc_auc": 0.9090686695610684
            },
            "16": {
                "loss": 0.05698399618268013,
                "roc_auc": 0.9080878695389872
            }
        },
        "25": {
            "0": {
                "loss": 0.05723138153553009,
                "roc_auc": 0.9085783370303249
            },
            "1": {
                "loss": 0.05701625347137451,
                "roc_auc": 0.9100008038246948
            },
            "2": {
                "loss": 0.05737723410129547,
                "roc_auc": 0.9086542527907762
            },
            "3": {
                "loss": 0.05717955902218819,
                "roc_auc": 0.9090847057993687
            },
            "4": {
                "loss": 0.057568397372961044,
                "roc_auc": 0.9082893466720349
            },
            "5": {
                "loss": 0.057440295815467834,
                "roc_auc": 0.908458157839464
            },
            "6": {
                "loss": 0.05724502354860306,
                "roc_auc": 0.9094281930835878
            },
            "7": {
                "loss": 0.05736308544874191,
                "roc_auc": 0.9098090712452397
            },
            "8": {
                "loss": 0.05721181258559227,
                "roc_auc": 0.9094396659162604
            },
            "9": {
                "loss": 0.05711745470762253,
                "roc_auc": 0.9089063634713956
            },
            "10": {
                "loss": 0.05806754529476166,
                "roc_auc": 0.9089902972311853
            },
            "11": {
                "loss": 0.058021821081638336,
                "roc_auc": 0.9090484466081936
            },
            "12": {
                "loss": 0.059492748230695724,
                "roc_auc": 0.9092505291776817
            },
            "13": {
                "loss": 0.05775627866387367,
                "roc_auc": 0.9088757067224853
            },
            "14": {
                "loss": 0.05778311938047409,
                "roc_auc": 0.9092932656163566
            },
            "15": {
                "loss": 0.057112861424684525,
                "roc_auc": 0.9101801029451709
            },
            "16": {
                "loss": 0.05690804123878479,
                "roc_auc": 0.9089573156326721
            }
        },
        "26": {
            "0": {
                "loss": 0.05683465674519539,
                "roc_auc": 0.9096925638595442
            },
            "1": {
                "loss": 0.056498076766729355,
                "roc_auc": 0.9108163120303248
            },
            "2": {
                "loss": 0.05653917044401169,
                "roc_auc": 0.9097713887872246
            },
            "3": {
                "loss": 0.056559253484010696,
                "roc_auc": 0.9099268953507678
            },
            "4": {
                "loss": 0.05676396191120148,
                "roc_auc": 0.9093780786360389
            },
            "5": {
                "loss": 0.056961789727211,
                "roc_auc": 0.9093916707362689
            },
            "6": {
                "loss": 0.0567326545715332,
                "roc_auc": 0.9104422038399401
            },
            "7": {
                "loss": 0.05714632198214531,
                "roc_auc": 0.9108081275678934
            },
            "8": {
                "loss": 0.057205937802791595,
                "roc_auc": 0.9103966162368129
            },
            "9": {
                "loss": 0.05720146745443344,
                "roc_auc": 0.9099183374210776
            },
            "10": {
                "loss": 0.05862780287861824,
                "roc_auc": 0.9098922379527224
            },
            "11": {
                "loss": 0.0580502450466156,
                "roc_auc": 0.9100951469805589
            },
            "12": {
                "loss": 0.05919945240020752,
                "roc_auc": 0.9102547844742598
            },
            "13": {
                "loss": 0.05741264671087265,
                "roc_auc": 0.9099212805335527
            },
            "14": {
                "loss": 0.05718116834759712,
                "roc_auc": 0.9103798517781809
            },
            "15": {
                "loss": 0.05674917250871658,
                "roc_auc": 0.9112036824742171
            },
            "16": {
                "loss": 0.05658828467130661,
                "roc_auc": 0.910087879522918
            }
        },
        "27": {
            "0": {
                "loss": 0.05664628744125366,
                "roc_auc": 0.9106960058717044
            },
            "1": {
                "loss": 0.056441780179739,
                "roc_auc": 0.911958112000428
            },
            "2": {
                "loss": 0.056700170040130615,
                "roc_auc": 0.9107374443010574
            },
            "3": {
                "loss": 0.056839704513549805,
                "roc_auc": 0.9110436595234715
            },
            "4": {
                "loss": 0.05756475031375885,
                "roc_auc": 0.9102749367415676
            },
            "5": {
                "loss": 0.057477906346321106,
                "roc_auc": 0.9104855900733146
            },
            "6": {
                "loss": 0.05771065130829811,
                "roc_auc": 0.911323839203974
            },
            "7": {
                "loss": 0.05724143981933594,
                "roc_auc": 0.91187711874973
            },
            "8": {
                "loss": 0.05676666274666786,
                "roc_auc": 0.9114675834641491
            },
            "9": {
                "loss": 0.0565013587474823,
                "roc_auc": 0.9108696319681384
            },
            "10": {
                "loss": 0.056767139583826065,
                "roc_auc": 0.911146723748541
            },
            "11": {
                "loss": 0.056754838675260544,
                "roc_auc": 0.9110244730461272
            },
            "12": {
                "loss": 0.05658292770385742,
                "roc_auc": 0.9116109744794771
            },
            "13": {
                "loss": 0.056681644171476364,
                "roc_auc": 0.9108871419984323
            },
            "14": {
                "loss": 0.057083286345005035,
                "roc_auc": 0.9113795038161161
            },
            "15": {
                "loss": 0.05716434493660927,
                "roc_auc": 0.9122778642941795
            },
            "16": {
                "loss": 0.05826790630817413,
                "roc_auc": 0.9108366662337958
            }
        },
        "28": {
            "0": {
                "loss": 0.05773017182946205,
                "roc_auc": 0.9118367448108975
            },
            "1": {
                "loss": 0.05866149067878723,
                "roc_auc": 0.9124499133058764
            },
            "2": {
                "loss": 0.05710575357079506,
                "roc_auc": 0.91196889395148
            },
            "3": {
                "loss": 0.05689374357461929,
                "roc_auc": 0.9116902375543874
            },
            "4": {
                "loss": 0.056611016392707825,
                "roc_auc": 0.9115327910972808
            },
            "5": {
                "loss": 0.05662521719932556,
                "roc_auc": 0.911254289753584
            },
            "6": {
                "loss": 0.05613064765930176,
                "roc_auc": 0.9125615371749801
            },
            "7": {
                "loss": 0.056478217244148254,
                "roc_auc": 0.9126806649514718
            },
            "8": {
                "loss": 0.05610814318060875,
                "roc_auc": 0.9125911678337476
            },
            "9": {
                "loss": 0.056181401014328,
                "roc_auc": 0.9116669232193036
            },
            "10": {
                "loss": 0.05649995431303978,
                "roc_auc": 0.9121708494134764
            },
            "11": {
                "loss": 0.056524116545915604,
                "roc_auc": 0.911860092985303
            },
            "12": {
                "loss": 0.0563017800450325,
                "roc_auc": 0.9126578008110615
            },
            "13": {
                "loss": 0.05640755966305733,
                "roc_auc": 0.9116954032340644
            },
            "14": {
                "loss": 0.05660486966371536,
                "roc_auc": 0.912500133851483
            },
            "15": {
                "loss": 0.05687466263771057,
                "roc_auc": 0.9129559956679736
            },
            "16": {
                "loss": 0.05737273022532463,
                "roc_auc": 0.9121168262864543
            }
        },
        "29": {
            "0": {
                "loss": 0.06071655452251434,
                "roc_auc": 0.9120779431070655
            },
            "1": {
                "loss": 0.05791947990655899,
                "roc_auc": 0.9139777263225756
            },
            "2": {
                "loss": 0.059502508491277695,
                "roc_auc": 0.9122958293215738
            },
            "3": {
                "loss": 0.05692557618021965,
                "roc_auc": 0.9128902246075419
            },
            "4": {
                "loss": 0.05653397738933563,
                "roc_auc": 0.91230230967606
            },
            "5": {
                "loss": 0.056418053805828094,
                "roc_auc": 0.9122350204886379
            },
            "6": {
                "loss": 0.05597436800599098,
                "roc_auc": 0.9134538758500046
            },
            "7": {
                "loss": 0.05652691423892975,
                "roc_auc": 0.9135271679669128
            },
            "8": {
                "loss": 0.0565333291888237,
                "roc_auc": 0.9135719127894691
            },
            "9": {
                "loss": 0.05777721852064133,
                "roc_auc": 0.9121987867565782
            },
            "10": {
                "loss": 0.0572693906724453,
                "roc_auc": 0.9131404510026453
            },
            "11": {
                "loss": 0.0574323795735836,
                "roc_auc": 0.9124910659695196
            },
            "12": {
                "loss": 0.05651215463876724,
                "roc_auc": 0.9135633033177538
            },
            "13": {
                "loss": 0.05634438991546631,
                "roc_auc": 0.9125100576811114
            },
            "14": {
                "loss": 0.056338876485824585,
                "roc_auc": 0.9132811981679915
            },
            "15": {
                "loss": 0.0562722273170948,
                "roc_auc": 0.9139519881541022
            },
            "16": {
                "loss": 0.05637668818235397,
                "roc_auc": 0.9128398732583953
            }
        }
    },
    "validating": {
        "0": {
            "0": {
                "loss": 0.8932621479034424,
                "roc_auc": 0.7156461263724665
            },
            "9": {
                "loss": 0.12909644842147827,
                "roc_auc": 0.29188773522550127
            }
        },
        "1": {
            "0": {
                "loss": 0.1020909994840622,
                "roc_auc": 0.6945767412616901
            },
            "9": {
                "loss": 0.0982084795832634,
                "roc_auc": 0.633266058568205
            }
        },
        "2": {
            "0": {
                "loss": 0.08975720405578613,
                "roc_auc": 0.6984941567666056
            },
            "9": {
                "loss": 0.08044349402189255,
                "roc_auc": 0.6932520039939367
            }
        },
        "3": {
            "0": {
                "loss": 0.07871659100055695,
                "roc_auc": 0.704284936838033
            },
            "9": {
                "loss": 0.07910069823265076,
                "roc_auc": 0.7096861333108714
            }
        },
        "4": {
            "0": {
                "loss": 0.07659205794334412,
                "roc_auc": 0.7109053521760205
            },
            "9": {
                "loss": 0.07510067522525787,
                "roc_auc": 0.7157641472047037
            }
        },
        "5": {
            "0": {
                "loss": 0.0742056742310524,
                "roc_auc": 0.7237592432501363
            },
            "9": {
                "loss": 0.07367809861898422,
                "roc_auc": 0.7357300920040662
            }
        },
        "6": {
            "0": {
                "loss": 0.07339904457330704,
                "roc_auc": 0.7462439756486289
            },
            "9": {
                "loss": 0.07309649139642715,
                "roc_auc": 0.7559415021987436
            }
        },
        "7": {
            "0": {
                "loss": 0.07276008278131485,
                "roc_auc": 0.7638264384557631
            },
            "9": {
                "loss": 0.07232842594385147,
                "roc_auc": 0.7725043960545268
            }
        },
        "8": {
            "0": {
                "loss": 0.07196179777383804,
                "roc_auc": 0.7797551194267652
            },
            "9": {
                "loss": 0.07158256322145462,
                "roc_auc": 0.7871451512744385
            }
        },
        "9": {
            "0": {
                "loss": 0.07127078622579575,
                "roc_auc": 0.7928645642824454
            },
            "9": {
                "loss": 0.07097551971673965,
                "roc_auc": 0.798582507953915
            }
        },
        "10": {
            "0": {
                "loss": 0.07122941315174103,
                "roc_auc": 0.8035850484062934
            },
            "9": {
                "loss": 0.07058364897966385,
                "roc_auc": 0.8066954231945505
            }
        },
        "11": {
            "0": {
                "loss": 0.07047758996486664,
                "roc_auc": 0.8086156668157013
            },
            "9": {
                "loss": 0.0703948438167572,
                "roc_auc": 0.8111209503345606
            }
        },
        "12": {
            "0": {
                "loss": 0.07012980431318283,
                "roc_auc": 0.8121152956753568
            },
            "9": {
                "loss": 0.0701332837343216,
                "roc_auc": 0.8137097591943743
            }
        },
        "13": {
            "0": {
                "loss": 0.07018690556287766,
                "roc_auc": 0.8151699651211992
            },
            "9": {
                "loss": 0.07306992262601852,
                "roc_auc": 0.8150841747864594
            }
        },
        "14": {
            "0": {
                "loss": 0.0699693113565445,
                "roc_auc": 0.8173283906221362
            },
            "9": {
                "loss": 0.0704178586602211,
                "roc_auc": 0.8176752956264661
            }
        },
        "15": {
            "0": {
                "loss": 0.0698496624827385,
                "roc_auc": 0.8189588239476658
            },
            "9": {
                "loss": 0.07042039185762405,
                "roc_auc": 0.8196525449622021
            }
        },
        "16": {
            "0": {
                "loss": 0.07029662281274796,
                "roc_auc": 0.8216048964805548
            },
            "9": {
                "loss": 0.07022322714328766,
                "roc_auc": 0.8225465196490722
            }
        },
        "17": {
            "0": {
                "loss": 0.06978841871023178,
                "roc_auc": 0.823106057751799
            },
            "9": {
                "loss": 0.06986956298351288,
                "roc_auc": 0.8241271271565134
            }
        },
        "18": {
            "0": {
                "loss": 0.06955536454916,
                "roc_auc": 0.8246680636204872
            },
            "9": {
                "loss": 0.06993815302848816,
                "roc_auc": 0.8257332068979513
            }
        },
        "19": {
            "0": {
                "loss": 0.06973849982023239,
                "roc_auc": 0.8263718890924916
            },
            "9": {
                "loss": 0.06984226405620575,
                "roc_auc": 0.8264405200533768
            }
        },
        "20": {
            "0": {
                "loss": 0.06925018876791,
                "roc_auc": 0.8273962534579413
            },
            "9": {
                "loss": 0.0713779553771019,
                "roc_auc": 0.8274522400964658
            }
        },
        "21": {
            "0": {
                "loss": 0.06911341845989227,
                "roc_auc": 0.8288283540449294
            },
            "9": {
                "loss": 0.0704895406961441,
                "roc_auc": 0.830382429790439
            }
        },
        "22": {
            "0": {
                "loss": 0.06905800104141235,
                "roc_auc": 0.8301089586291315
            },
            "9": {
                "loss": 0.06894373893737793,
                "roc_auc": 0.8310125691714914
            }
        },
        "23": {
            "0": {
                "loss": 0.07057633996009827,
                "roc_auc": 0.8309255559454785
            },
            "9": {
                "loss": 0.07136698812246323,
                "roc_auc": 0.8312212852837957
            }
        },
        "24": {
            "0": {
                "loss": 0.06987791508436203,
                "roc_auc": 0.8318114018917123
            },
            "9": {
                "loss": 0.06873106956481934,
                "roc_auc": 0.8332004358576177
            }
        },
        "25": {
            "0": {
                "loss": 0.0687929168343544,
                "roc_auc": 0.83359646375093
            },
            "9": {
                "loss": 0.06917176395654678,
                "roc_auc": 0.8350236092945004
            }
        },
        "26": {
            "0": {
                "loss": 0.06871214509010315,
                "roc_auc": 0.8350989639792092
            },
            "9": {
                "loss": 0.06942376494407654,
                "roc_auc": 0.8360961848259225
            }
        },
        "27": {
            "0": {
                "loss": 0.06855133175849915,
                "roc_auc": 0.836060814640653
            },
            "9": {
                "loss": 0.0686890184879303,
                "roc_auc": 0.8369791574444172
            }
        },
        "28": {
            "0": {
                "loss": 0.06970388442277908,
                "roc_auc": 0.8379261323958874
            },
            "9": {
                "loss": 0.06840389966964722,
                "roc_auc": 0.8377366735538658
            }
        },
        "29": {
            "0": {
                "loss": 0.0725105032324791,
                "roc_auc": 0.8374728097126738
            },
            "9": {
                "loss": 0.07007954269647598,
                "roc_auc": 0.8380363226787901
            }
        },
        "30": {
            "0": {
                "loss": 0.06865283846855164,
                "roc_auc": 0.8394953775942107
            }
        }
    },
    "testing": {
        "0": {
            "0": {
                "loss": 0.893353283405304,
                "roc_auc": 0.7187824876224197
            },
            "9": {
                "loss": 0.1297304630279541,
                "roc_auc": 0.28762613394520836
            }
        },
        "1": {
            "0": {
                "loss": 0.1023058295249939,
                "roc_auc": 0.6941874171543473
            },
            "9": {
                "loss": 0.09845705330371857,
                "roc_auc": 0.6309841776292655
            }
        },
        "2": {
            "0": {
                "loss": 0.0899331197142601,
                "roc_auc": 0.6980602339737033
            },
            "9": {
                "loss": 0.08053924888372421,
                "roc_auc": 0.6927363292142485
            }
        },
        "3": {
            "0": {
                "loss": 0.07872852683067322,
                "roc_auc": 0.7037294168993318
            },
            "9": {
                "loss": 0.07905874401330948,
                "roc_auc": 0.7090489020759542
            }
        },
        "4": {
            "0": {
                "loss": 0.07653214037418365,
                "roc_auc": 0.7101748837901468
            },
            "9": {
                "loss": 0.07501725852489471,
                "roc_auc": 0.7149722289720256
            }
        },
        "5": {
            "0": {
                "loss": 0.07409486174583435,
                "roc_auc": 0.7230135656577986
            },
            "9": {
                "loss": 0.07353249937295914,
                "roc_auc": 0.7352021364295732
            }
        },
        "6": {
            "0": {
                "loss": 0.07322081923484802,
                "roc_auc": 0.7460578101995655
            },
            "9": {
                "loss": 0.07288248836994171,
                "roc_auc": 0.7561774609253648
            }
        },
        "7": {
            "0": {
                "loss": 0.07251717895269394,
                "roc_auc": 0.7644781504701974
            },
            "9": {
                "loss": 0.07205591350793839,
                "roc_auc": 0.7737402016005654
            }
        },
        "8": {
            "0": {
                "loss": 0.0716642364859581,
                "roc_auc": 0.7815374667967271
            },
            "9": {
                "loss": 0.0712585300207138,
                "roc_auc": 0.7894586114666836
            }
        },
        "9": {
            "0": {
                "loss": 0.07092558592557907,
                "roc_auc": 0.7955331305324007
            },
            "9": {
                "loss": 0.07060787081718445,
                "roc_auc": 0.8015350730639784
            }
        },
        "10": {
            "0": {
                "loss": 0.07083390653133392,
                "roc_auc": 0.8067413097742209
            },
            "9": {
                "loss": 0.07017874717712402,
                "roc_auc": 0.8099891820268468
            }
        },
        "11": {
            "0": {
                "loss": 0.0700666680932045,
                "roc_auc": 0.8120167675395508
            },
            "9": {
                "loss": 0.06996320933103561,
                "roc_auc": 0.8146374474795107
            }
        },
        "12": {
            "0": {
                "loss": 0.06969349831342697,
                "roc_auc": 0.8157130956733842
            },
            "9": {
                "loss": 0.0696837529540062,
                "roc_auc": 0.8173613322670763
            }
        },
        "13": {
            "0": {
                "loss": 0.06972652673721313,
                "roc_auc": 0.8188323269511704
            },
            "9": {
                "loss": 0.072625070810318,
                "roc_auc": 0.8187418108071914
            }
        },
        "14": {
            "0": {
                "loss": 0.06950599700212479,
                "roc_auc": 0.8209986230748239
            },
            "9": {
                "loss": 0.0699630081653595,
                "roc_auc": 0.8213585382283211
            }
        },
        "15": {
            "0": {
                "loss": 0.06938808411359787,
                "roc_auc": 0.8226413462763271
            },
            "9": {
                "loss": 0.06996151804924011,
                "roc_auc": 0.8233161006659762
            }
        },
        "16": {
            "0": {
                "loss": 0.06982112675905228,
                "roc_auc": 0.8252380945487005
            },
            "9": {
                "loss": 0.06974812597036362,
                "roc_auc": 0.8261491412436918
            }
        },
        "17": {
            "0": {
                "loss": 0.06931754946708679,
                "roc_auc": 0.8266988745947323
            },
            "9": {
                "loss": 0.06939807534217834,
                "roc_auc": 0.8276936815771874
            }
        },
        "18": {
            "0": {
                "loss": 0.06908761709928513,
                "roc_auc": 0.828228995663889
            },
            "9": {
                "loss": 0.06946825981140137,
                "roc_auc": 0.8292751843202198
            }
        },
        "19": {
            "0": {
                "loss": 0.0692703127861023,
                "roc_auc": 0.8299045584257424
            },
            "9": {
                "loss": 0.06938481330871582,
                "roc_auc": 0.8299554060923945
            }
        },
        "20": {
            "0": {
                "loss": 0.06878931820392609,
                "roc_auc": 0.8309009344511511
            },
            "9": {
                "loss": 0.07092609256505966,
                "roc_auc": 0.8309409566772656
            }
        },
        "21": {
            "0": {
                "loss": 0.06865327805280685,
                "roc_auc": 0.8323110112832028
            },
            "9": {
                "loss": 0.07002142071723938,
                "roc_auc": 0.833821756843557
            }
        },
        "22": {
            "0": {
                "loss": 0.068599633872509,
                "roc_auc": 0.8335704187223177
            },
            "9": {
                "loss": 0.06848347187042236,
                "roc_auc": 0.8344655084477468
            }
        },
        "23": {
            "0": {
                "loss": 0.07012440264225006,
                "roc_auc": 0.834364708710706
            },
            "9": {
                "loss": 0.07091536372900009,
                "roc_auc": 0.8346684158314014
            }
        },
        "24": {
            "0": {
                "loss": 0.06942205131053925,
                "roc_auc": 0.835279027200182
            },
            "9": {
                "loss": 0.06827139109373093,
                "roc_auc": 0.8366482303536195
            }
        },
        "25": {
            "0": {
                "loss": 0.06833834946155548,
                "roc_auc": 0.8370157181939376
            },
            "9": {
                "loss": 0.06871066987514496,
                "roc_auc": 0.8383825446145616
            }
        },
        "26": {
            "0": {
                "loss": 0.0682496726512909,
                "roc_auc": 0.8384775610950852
            },
            "9": {
                "loss": 0.06895902752876282,
                "roc_auc": 0.8394417250191982
            }
        },
        "27": {
            "0": {
                "loss": 0.06809012591838837,
                "roc_auc": 0.8394344998861353
            },
            "9": {
                "loss": 0.06822796911001205,
                "roc_auc": 0.8403293710397057
            }
        },
        "28": {
            "0": {
                "loss": 0.06924153864383698,
                "roc_auc": 0.8412382515465394
            },
            "9": {
                "loss": 0.0679449513554573,
                "roc_auc": 0.8410837941844503
            }
        },
        "29": {
            "0": {
                "loss": 0.07205826044082642,
                "roc_auc": 0.8408056816482005
            },
            "9": {
                "loss": 0.06961898505687714,
                "roc_auc": 0.8413946655880784
            }
        },
        "30": {
            "0": {
                "loss": 0.06818884611129761,
                "roc_auc": 0.8428203225523069
            }
        }
    },
    "accuracy": {
        "0": {
            "precision": {
                "constant": 0.3387824063643046,
                "relative": 0.33161646323016614
            },
            "recall": {
                "constant": 0.5575320265276499,
                "relative": 0.7493285586392122
            }
        },
        "1": {
            "precision": {
                "constant": 0.0065097838598286205,
                "relative": 0.0065097838598286205
            },
            "recall": {
                "constant": 0.0005550132504241791,
                "relative": 0.0005550132504241791
            }
        },
        "2": {
            "precision": {
                "constant": 0.016351599509612045,
                "relative": 0.016351599509612045
            },
            "recall": {
                "constant": 0.0031264210486502274,
                "relative": 0.0031264210486502274
            }
        },
        "3": {
            "precision": {
                "constant": 0.013576330445717518,
                "relative": 0.013576330445717518
            },
            "recall": {
                "constant": 0.004955812794849421,
                "relative": 0.004955812794849421
            }
        },
        "4": {
            "precision": {
                "constant": 0.013584176656635118,
                "relative": 0.013584176656635118
            },
            "recall": {
                "constant": 0.0041253896184701,
                "relative": 0.0041253896184701
            }
        },
        "5": {
            "precision": {
                "constant": 0.01560205747202166,
                "relative": 0.01560205747202166
            },
            "recall": {
                "constant": 0.0033578236481409864,
                "relative": 0.0033578236481409864
            }
        },
        "6": {
            "precision": {
                "constant": 0.01650154716963132,
                "relative": 0.01650154716963132
            },
            "recall": {
                "constant": 0.0031743620165814094,
                "relative": 0.0031743620165814094
            }
        },
        "7": {
            "precision": {
                "constant": 0.017049588479758574,
                "relative": 0.017049588479758574
            },
            "recall": {
                "constant": 0.0031743620165814094,
                "relative": 0.0031743620165814094
            }
        },
        "8": {
            "precision": {
                "constant": 0.01747932386920748,
                "relative": 0.01747932386920748
            },
            "recall": {
                "constant": 0.0031679673369548584,
                "relative": 0.0031679673369548584
            }
        },
        "9": {
            "precision": {
                "constant": 0.01676845610372915,
                "relative": 0.01676845610372915
            },
            "recall": {
                "constant": 0.002391000440079726,
                "relative": 0.002391000440079726
            }
        },
        "10": {
            "precision": {
                "constant": 0.015345171589576238,
                "relative": 0.015345171589576238
            },
            "recall": {
                "constant": 0.002116676341710139,
                "relative": 0.002116676341710139
            }
        },
        "11": {
            "precision": {
                "constant": 0.014065663024928916,
                "relative": 0.014065663024928916
            },
            "recall": {
                "constant": 0.0014607889140578981,
                "relative": 0.0014607889140578981
            }
        },
        "12": {
            "precision": {
                "constant": 0.015142116910245824,
                "relative": 0.015142116910245824
            },
            "recall": {
                "constant": 0.0015589648624152156,
                "relative": 0.0015589648624152156
            }
        },
        "13": {
            "precision": {
                "constant": 0.01853417148851347,
                "relative": 0.01853417148851347
            },
            "recall": {
                "constant": 0.0029270801641413497,
                "relative": 0.0029270801641413497
            }
        },
        "14": {
            "precision": {
                "constant": 0.019846340370064632,
                "relative": 0.019846340370064632
            },
            "recall": {
                "constant": 0.0032825444455731522,
                "relative": 0.0032825444455731522
            }
        },
        "15": {
            "precision": {
                "constant": 0.018428449348324022,
                "relative": 0.018428449348324022
            },
            "recall": {
                "constant": 0.0030342285380119557,
                "relative": 0.0030342285380119557
            }
        },
        "16": {
            "precision": {
                "constant": 0.030554361696639554,
                "relative": 0.030554361696639554
            },
            "recall": {
                "constant": 0.010910077030331746,
                "relative": 0.010910077030331746
            }
        },
        "17": {
            "precision": {
                "constant": 0.029257647866353653,
                "relative": 0.029257647866353653
            },
            "recall": {
                "constant": 0.010274112552848805,
                "relative": 0.010274112552848805
            }
        },
        "18": {
            "precision": {
                "constant": 0.030449894972717252,
                "relative": 0.030449894972717252
            },
            "recall": {
                "constant": 0.011553959854783205,
                "relative": 0.011553959854783205
            }
        },
        "19": {
            "precision": {
                "constant": 0.03559289572750177,
                "relative": 0.03559289572750177
            },
            "recall": {
                "constant": 0.0161906799935039,
                "relative": 0.0161906799935039
            }
        },
        "20": {
            "precision": {
                "constant": 0.030473635413693696,
                "relative": 0.030473635413693696
            },
            "recall": {
                "constant": 0.011892832268213112,
                "relative": 0.011892832268213112
            }
        },
        "21": {
            "precision": {
                "constant": 0.03328148234553438,
                "relative": 0.03328148234553438
            },
            "recall": {
                "constant": 0.014322546978673769,
                "relative": 0.014322546978673769
            }
        },
        "22": {
            "precision": {
                "constant": 0.03330527431532141,
                "relative": 0.03330527431532141
            },
            "recall": {
                "constant": 0.014657228769216385,
                "relative": 0.014657228769216385
            }
        },
        "23": {
            "precision": {
                "constant": 0.026189357216530845,
                "relative": 0.026189357216530845
            },
            "recall": {
                "constant": 0.009720661079313218,
                "relative": 0.009720661079313218
            }
        },
        "24": {
            "precision": {
                "constant": 0.02882930078543328,
                "relative": 0.02882930078543328
            },
            "recall": {
                "constant": 0.011194772280896234,
                "relative": 0.011194772280896234
            }
        },
        "25": {
            "precision": {
                "constant": 0.03811979730352389,
                "relative": 0.03811979730352389
            },
            "recall": {
                "constant": 0.017991219636910017,
                "relative": 0.017991219636910017
            }
        },
        "26": {
            "precision": {
                "constant": 0.04872394813145563,
                "relative": 0.04872394813145563
            },
            "recall": {
                "constant": 0.029173660448513977,
                "relative": 0.029173660448513977
            }
        },
        "27": {
            "precision": {
                "constant": 0.0454643408413899,
                "relative": 0.0454643408413899
            },
            "recall": {
                "constant": 0.027417053492321236,
                "relative": 0.027417053492321236
            }
        },
        "28": {
            "precision": {
                "constant": 0.061590910401837985,
                "relative": 0.061592054712929035
            },
            "recall": {
                "constant": 0.039215451158030074,
                "relative": 0.039513869540602445
            }
        },
        "29": {
            "precision": {
                "constant": 0.028783819783363977,
                "relative": 0.028783819783363977
            },
            "recall": {
                "constant": 0.015718665218428338,
                "relative": 0.015718665218428338
            }
        },
        "30": {
            "precision": {
                "constant": 0.057838395991081606,
                "relative": 0.05783977330669349
            },
            "recall": {
                "constant": 0.03626647749286917,
                "relative": 0.036564895875441525
            }
        }
    }
}